asyncsql/__init__.py
asyncsql/backends.py
asyncsql/cursor.py
asyncsql/exceptions.py
asyncsql/helpers.py
asyncsql/models.py
asyncsql/queries.py
asyncsql/settings.py
asyncsql/migrate/__init__.py
asyncsql/migrate/__main__.py
asyncsql-0.1.4.dist-info/LICENSE
asyncsql-0.1.4.dist-info/METADATA
asyncsql-0.1.4.dist-info/WHEEL
asyncsql-0.1.4.dist-info/top_level.txt
asyncsql-0.1.4.dist-info/zip-safe
asyncsql-0.1.4.dist-info/RECORD
