Metadata-Version: 2.1
Name: asyncsql
Version: 0.1.4
Summary: Yet another async SQL lib.
Home-page: https://gitlab.com/toopy/asyncsql
Author: Florent Pigout
Author-email: florent@toopy.org
License: MIT
Keywords: asyncio,sql
Classifier: Development Status :: 4 - Beta
Classifier: Intended Audience :: Developers
Classifier: License :: OSI Approved :: MIT License
Classifier: Natural Language :: English
Classifier: Programming Language :: Python :: 3.8
License-File: LICENSE
Requires-Dist: aiofiles
Requires-Dist: asyncpg
Requires-Dist: cached-property
Requires-Dist: dynaconf
Requires-Dist: immutables
Requires-Dist: orjson
Requires-Dist: pydantic
Provides-Extra: lint
Requires-Dist: black; extra == "lint"
Requires-Dist: flake8; extra == "lint"
Requires-Dist: isort; extra == "lint"
Requires-Dist: pre-commit; extra == "lint"
Provides-Extra: release
Requires-Dist: check-manifest; extra == "release"
Requires-Dist: wheel[signatures]; extra == "release"
Requires-Dist: zest.releaser; extra == "release"
Provides-Extra: test
Requires-Dist: async-generator; extra == "test"
Requires-Dist: pytest-asyncio; extra == "test"
Requires-Dist: pytest-cov; extra == "test"
Requires-Dist: pytest-lazy-fixture; extra == "test"
Requires-Dist: pytest-mock; extra == "test"
Requires-Dist: pytest<8; extra == "test"
